gradebook/.mypy.ini
gradebook/cleanup_db.py
gradebook/cli.py
gradebook/db.py
gradebook/debug_add.py
gradebook/gradebook_debug.py
gradebook/models/__init__.py
gradebook-0.1.4.dist-info/METADATA
gradebook-0.1.4.dist-info/WHEEL
gradebook-0.1.4.dist-info/entry_points.txt
gradebook-0.1.4.dist-info/RECORD
